alsacommonutils/__init__.py
alsacommonutils/al_common_aws_utils.py
alsacommonutils/al_common_emoji_skin_tone.py
alsacommonutils/al_common_utils.py
alsacommonutils-0.3.dist-info/LICENSE.txt
alsacommonutils-0.3.dist-info/METADATA
alsacommonutils-0.3.dist-info/WHEEL
alsacommonutils-0.3.dist-info/top_level.txt
alsacommonutils-0.3.dist-info/RECORD
