Metadata-Version: 2.1
Name: alsacommonutils
Version: 0.3
Summary: Provides general useful common function as well as AWS specific functions. Added the Fitzpatrick scale for emoji skin tone
Home-page: https://al.co.za/
Author: Autumn Leaf IT South Africa
Author-email: jason@al.co.za
Classifier: Programming Language :: Python :: 3
Classifier: License :: OSI Approved :: MIT License
Classifier: Operating System :: OS Independent
License-File: LICENSE.txt
